quant_vbt/__init__.py
quant_vbt/analyzer.py
quant_vbt/optimizer.py
quant_vbt/stats.py
quant_vbt/strategy.py
quant_vbt/utils.py
quant_vbt-0.1.6.3.dist-info/METADATA
quant_vbt-0.1.6.3.dist-info/WHEEL
quant_vbt-0.1.6.3.dist-info/top_level.txt
quant_vbt-0.1.6.3.dist-info/RECORD
