Metadata-Version: 2.4
Name: quant-vbt
Version: 0.1.6.3
Summary: Lightweight Vectorbt extension with in-built statistical backtesting methods
Author-email: Dein Name <deine@mail.de>
License: MIT
Classifier: Programming Language :: Python :: 3
Classifier: License :: OSI Approved :: MIT License
Classifier: Operating System :: OS Independent
Requires-Python: >=3.8
Requires-Dist: pandas
Requires-Dist: numpy
Requires-Dist: vectorbt
Requires-Dist: pandas_ta
Requires-Dist: hyperopt
